RPA_Cloud_AWS.libspec
RPA/Cloud/AWS/__init__.py
RPA/Cloud/AWS/textract.py
rpaframework_aws-5.3.4.dist-info/LICENSE
rpaframework_aws-5.3.4.dist-info/METADATA
rpaframework_aws-5.3.4.dist-info/WHEEL
rpaframework_aws-5.3.4.dist-info/RECORD
