Metadata-Version: 2.1
Name: rpaframework-aws
Version: 5.3.4
Summary: AWS library for RPA Framework
Home-page: https://rpaframework.org/
License: Apache-2.0
Keywords: robotframework,rpa,automation,aws
Author: RPA Framework
Author-email: rpafw@robocorp.com
Requires-Python: >=3.9,<4.0
Classifier: Development Status :: 5 - Production/Stable
Classifier: Framework :: Robot Framework
Classifier: Framework :: Robot Framework :: Library
Classifier: Intended Audience :: Developers
Classifier: License :: OSI Approved :: Apache Software License
Classifier: Operating System :: OS Independent
Classifier: Programming Language :: Python :: 3
Classifier: Programming Language :: Python :: 3.9
Classifier: Programming Language :: Python :: 3.10
Classifier: Programming Language :: Python :: 3.11
Classifier: Programming Language :: Python :: 3.12
Classifier: Programming Language :: Python :: 3.8
Classifier: Topic :: Software Development :: Libraries
Classifier: Topic :: Software Development :: Libraries :: Python Modules
Requires-Dist: amazon-textract-response-parser (>=0.1.33,<0.2.0)
Requires-Dist: boto3 (>=1.35.90,<2.0.0)
Requires-Dist: robotframework (>=4.0.0,!=4.0.1,!=6.1.0,<7.0.0)
Requires-Dist: robotframework-pythonlibcore (>=4.2.0,<5.0.0)
Requires-Dist: rpaframework-core (>=11.3.1,<12.0.0)
Requires-Dist: urllib3 (>=1.25.4,<1.27)
Project-URL: Documentation, https://rpaframework.org/
Project-URL: Repository, https://github.com/robocorp/rpaframework
